easyenrichment/__init__.py
easyenrichment/client.py
easyenrichment/exceptions.py
easyenrichment/types.py
easyenrichment-1.0.0.dist-info/METADATA
easyenrichment-1.0.0.dist-info/WHEEL
easyenrichment-1.0.0.dist-info/licenses/LICENSE
easyenrichment-1.0.0.dist-info/RECORD
