Metadata-Version: 2.4
Name: easyenrichment
Version: 1.0.0
Summary: Transaction Enrichment API — enrich bank transactions with merchant name, logo, category, and more. Alternative to Plaid Enrich, Ntropy, and Mastercard Ethoca.
Project-URL: Homepage, https://easyenrichment.com
Project-URL: Repository, https://github.com/AI-Factory-Dev/easyenrichment-api
Project-URL: Documentation, https://easyenrichment.com/docs
Project-URL: Bug Tracker, https://github.com/AI-Factory-Dev/easyenrichment-api/issues
Author-email: Easy Enrichment <hello@easyenrichment.com>
License-Expression: MIT
License-File: LICENSE
Keywords: accounting automation,ai transaction,ai-enrichment,bank statement parser,bank transaction parser,bank-transactions,banking api,banking-api,bookkeeping,brand identification,carbon footprint,claude ai,co2 tracking,credit card transaction,debit card transaction,easy-enrichment,easyenrichment,expense categorization,expense management,expense tracking,financial api,financial data,fintech,fintech api,logo api,mastercard ethoca alternative,mcc code lookup,mcc-code,merchant categorization,merc
Classifier: Development Status :: 4 - Beta
Classifier: Intended Audience :: Developers
Classifier: Intended Audience :: Financial and Insurance Industry
Classifier: License :: OSI Approved :: MIT License
Classifier: Programming Language :: Python :: 3
Classifier: Topic :: Office/Business :: Financial
Classifier: Topic :: Software Development :: Libraries :: Python Modules
Requires-Python: >=3.8
Requires-Dist: requests>=2.20.0
